{
    "html.autoClosingTags": true,
    "diagnostic.virtualText": true,
   "diagnostic.checkCurrentLine": true, 
    "diagnostic.displayByAle": true, 
    "java.home": "/Users/kerman/.sdkman/candidates/java/16.0.1-zulu/",
    "coc.preferences.formatOnSaveFiletypes": [
        "javascript"

    ],

    "explorer.icon.source": "vim-devicons",
    "explorer.icon.enableNerdfont": true,
    "explorer.file.showHiddenFiles": true,
    "explorer.keyMappings": {
        "s": "open:vsplit",
        "mm": "rename",
        "mc": "copyFile",
        "C": "copyFile",
        "md": "delete",
        "D": "delete",
        "ma": "addFile",
        "mA": "addDirectory"
    },
    "suggest.completionItemKindLabels": {
    "method": "  ",
    "function": "  ",
    "variable": "[]",
    "field": "  ",
    "typeParameter": "<>",
    "constant": "  ",
    "class": " פּ ",
    "interface": " 蘒",
    "struct": "  ",
    "event": "  ",
    "operator": "  ",
    "module": "  ",
    "property": "  ",
    "enum": " 練",
    "reference": "  ",
    "keyword": "  ",
    "file": "  ",
    "folder": " ﱮ ",
    "color": "  ",
    "unit": " 塞 ",
    "snippet": "  ",
    "text": "  ",
    "constructor": "  ",
    "value": "  ",
    "enumMember": "  "
  },
    "explorer.file.child.template": "[git | 2] [selection | clip | 1] [indent][icon | 1] [diagnosticError & 1][filename omitCenter 1][modified][readonly] [linkIcon & 1][link growRight 1 omitCenter 5]",
    "python.linting.enabled":true,
    "python.linting.pylintEnabled":true
}

